adjacent_attention_network/__init__.py
adjacent_attention_network/adjacent_attention_network.py
adjacent_attention_pytorch-0.0.12.dist-info/LICENSE
adjacent_attention_pytorch-0.0.12.dist-info/METADATA
adjacent_attention_pytorch-0.0.12.dist-info/WHEEL
adjacent_attention_pytorch-0.0.12.dist-info/top_level.txt
adjacent_attention_pytorch-0.0.12.dist-info/RECORD
