Metadata-Version: 2.1
Name: adjacent-attention-pytorch
Version: 0.0.12
Summary: Adjacent Attention Network - Pytorch
Home-page: https://github.com/lucidrains/adjacent-attention-pytorch
Author: Phil Wang
Author-email: lucidrains@gmail.com
License: MIT
Keywords: artificial intelligence,attention mechanism,graph neural network,transformers
Classifier: Development Status :: 4 - Beta
Classifier: Intended Audience :: Developers
Classifier: Topic :: Scientific/Engineering :: Artificial Intelligence
Classifier: License :: OSI Approved :: MIT License
Classifier: Programming Language :: Python :: 3.6
License-File: LICENSE
Requires-Dist: einops (>=0.3)
Requires-Dist: torch (>=1.6)
Requires-Dist: isab-pytorch (<0.2)
